{
  "id": 3342386,
  "boosts": 82,
  "date_created": "2022-08-05T18:28:51.000Z",
  "death_count": null,
  "die_reason": 2,
  "duration": 824,
  "flags": 2,
  "flappycombo": 0,
  "gamemode_id": 6,
  "kill_count": 4,
  "killer_level": 120,
  "killer_name": "The Immortal",
  "killer_user_id": 20727913,
  "level": 28,
  "max_leaderboard": 14,
  "name": "Rouge",
  "room_id": null,
  "score": 249553,
  "team_id": null,
  "time_to_last": null,
  "user_id": 757772,
  "won": null,
  "coins_earned": 5,
  "killer_tribe_id": 17216,
  "killer_tribe_name": "?",
  "victim_tribe_id": 17288,
  "victim_tribe_name": "Abyss",
  "archived_at": "2025-06-08T02:09:22.932Z"
}