{
  "id": 6798970,
  "boosts": 30,
  "date_created": "2022-11-01T18:49:03.000Z",
  "death_count": null,
  "die_reason": 2,
  "duration": 206,
  "flags": null,
  "flappycombo": 0,
  "gamemode_id": 6,
  "kill_count": 2,
  "killer_level": 11,
  "killer_name": "W0W",
  "killer_user_id": 20946046,
  "level": 21,
  "max_leaderboard": null,
  "name": "West ",
  "room_id": null,
  "score": 107481,
  "team_id": null,
  "time_to_last": null,
  "user_id": 741088,
  "won": null,
  "coins_earned": 1,
  "killer_tribe_id": 27604,
  "killer_tribe_name": "_",
  "victim_tribe_id": 27586,
  "victim_tribe_name": "Crabs"
}