{
  "id": 708660,
  "boosts": 61,
  "date_created": "2022-05-24T02:23:04.000Z",
  "death_count": null,
  "die_reason": 2,
  "duration": 678,
  "flags": 2,
  "flappycombo": 0,
  "gamemode_id": 6,
  "kill_count": 16,
  "killer_level": 106,
  "killer_name": "yyds",
  "killer_user_id": 20938910,
  "level": 15,
  "max_leaderboard": 15,
  "name": "BOB 我愛阿神",
  "room_id": null,
  "score": 305854,
  "team_id": null,
  "time_to_last": null,
  "user_id": 840953,
  "won": null,
  "coins_earned": 8,
  "killer_tribe_id": 183,
  "killer_tribe_name": "泥巴魚",
  "victim_tribe_id": null,
  "victim_tribe_name": null,
  "archived_at": "2025-05-27T02:26:33.085Z"
}