{
  "id": 3757533,
  "boosts": 46,
  "date_created": "2022-08-17T00:34:13.000Z",
  "death_count": null,
  "die_reason": 2,
  "duration": 358,
  "flags": 2,
  "flappycombo": 0,
  "gamemode_id": 6,
  "kill_count": 1,
  "killer_level": 31,
  "killer_name": "c",
  "killer_user_id": 20817351,
  "level": 61,
  "max_leaderboard": null,
  "name": "Goofy",
  "room_id": null,
  "score": 122005,
  "team_id": null,
  "time_to_last": null,
  "user_id": 20691611,
  "won": null,
  "coins_earned": 2,
  "killer_tribe_id": 3366,
  "killer_tribe_name": "sus",
  "victim_tribe_id": 3295,
  "victim_tribe_name": "💀",
  "archived_at": "2025-06-10T07:27:14.088Z"
}