{
  "id": 6734396,
  "boosts": 344,
  "date_created": "2022-10-31T08:59:27.000Z",
  "death_count": null,
  "die_reason": 2,
  "duration": 1948,
  "flags": null,
  "flappycombo": 0,
  "gamemode_id": 1,
  "kill_count": 16,
  "killer_level": 11,
  "killer_name": null,
  "killer_user_id": 20963158,
  "level": 22,
  "max_leaderboard": 1,
  "name": "EL",
  "room_id": null,
  "score": 2398927,
  "team_id": null,
  "time_to_last": null,
  "user_id": 20938338,
  "won": null,
  "coins_earned": 35,
  "killer_tribe_id": null,
  "killer_tribe_name": null,
  "victim_tribe_id": null,
  "victim_tribe_name": null
}