{
  "id": 1512957,
  "boosts": 26,
  "date_created": "2022-06-14T07:14:31.000Z",
  "death_count": 0,
  "die_reason": 7,
  "duration": 717,
  "flags": null,
  "flappycombo": 0,
  "gamemode_id": 2,
  "kill_count": 10,
  "killer_level": null,
  "killer_name": null,
  "killer_user_id": null,
  "level": 61,
  "max_leaderboard": null,
  "name": "AKA_副團長꧁紅⚔️暈꧂",
  "room_id": 111764,
  "score": 457986,
  "team_id": 0,
  "time_to_last": null,
  "user_id": 20739035,
  "won": true,
  "coins_earned": 5,
  "killer_tribe_id": null,
  "killer_tribe_name": null,
  "victim_tribe_id": null,
  "victim_tribe_name": null,
  "archived_at": "2025-05-30T12:47:44.072Z"
}