{
  "id": 2045507,
  "boosts": 14,
  "date_created": "2022-06-28T17:10:07.000Z",
  "death_count": null,
  "die_reason": 3,
  "duration": 186,
  "flags": null,
  "flappycombo": 0,
  "gamemode_id": 6,
  "kill_count": 0,
  "killer_level": null,
  "killer_name": null,
  "killer_user_id": null,
  "level": 3,
  "max_leaderboard": null,
  "name": "<BLU>안녕하세요",
  "room_id": null,
  "score": 23710,
  "team_id": null,
  "time_to_last": null,
  "user_id": 20950835,
  "won": null,
  "coins_earned": 0,
  "killer_tribe_id": null,
  "killer_tribe_name": null,
  "victim_tribe_id": null,
  "victim_tribe_name": null,
  "archived_at": "2025-06-01T19:21:02.557Z"
}