{
  "id": 2106026,
  "boosts": 26,
  "date_created": "2022-06-30T10:16:22.000Z",
  "death_count": null,
  "die_reason": 2,
  "duration": 225,
  "flags": null,
  "flappycombo": 0,
  "gamemode_id": 6,
  "kill_count": 1,
  "killer_level": 58,
  "killer_name": "우거지국",
  "killer_user_id": null,
  "level": 74,
  "max_leaderboard": null,
  "name": "蟹蟹你",
  "room_id": null,
  "score": 78647,
  "team_id": null,
  "time_to_last": null,
  "user_id": 20822139,
  "won": null,
  "coins_earned": 0,
  "killer_tribe_id": 8349,
  "killer_tribe_name": "눈물의요정",
  "victim_tribe_id": 8373,
  "victim_tribe_name": "蜘蛛蟹",
  "archived_at": "2025-06-02T02:14:08.624Z"
}