{
  "id": 5716343,
  "boosts": 115,
  "date_created": "2022-10-06T06:11:02.000Z",
  "death_count": 6,
  "die_reason": 7,
  "duration": 1370,
  "flags": null,
  "flappycombo": 0,
  "gamemode_id": 2,
  "kill_count": 8,
  "killer_level": null,
  "killer_name": null,
  "killer_user_id": null,
  "level": 73,
  "max_leaderboard": null,
  "name": "ESL",
  "room_id": 140388,
  "score": 1908809,
  "team_id": 0,
  "time_to_last": null,
  "user_id": 20949037,
  "won": true,
  "coins_earned": 9,
  "killer_tribe_id": null,
  "killer_tribe_name": null,
  "victim_tribe_id": null,
  "victim_tribe_name": null,
  "archived_at": "2025-06-23T06:26:44.265Z"
}