{
  "id": 3931341,
  "boosts": 47,
  "date_created": "2022-08-21T08:34:02.000Z",
  "death_count": null,
  "die_reason": 2,
  "duration": 500,
  "flags": null,
  "flappycombo": 0,
  "gamemode_id": 6,
  "kill_count": 8,
  "killer_level": 24,
  "killer_name": "海洋深物",
  "killer_user_id": 20961045,
  "level": 66,
  "max_leaderboard": 12,
  "name": "DG",
  "room_id": null,
  "score": 491216,
  "team_id": null,
  "time_to_last": null,
  "user_id": 787333,
  "won": null,
  "coins_earned": 8,
  "killer_tribe_id": 7562,
  "killer_tribe_name": "999座車",
  "victim_tribe_id": 7569,
  "victim_tribe_name": " fu",
  "archived_at": "2025-06-11T04:50:04.454Z"
}