{
  "id": 1347798,
  "boosts": 2,
  "date_created": "2022-06-10T02:25:27.000Z",
  "death_count": null,
  "die_reason": 2,
  "duration": 212,
  "flags": null,
  "flappycombo": 0,
  "gamemode_id": 6,
  "kill_count": 0,
  "killer_level": 32,
  "killer_name": "111",
  "killer_user_id": 20940569,
  "level": 105,
  "max_leaderboard": null,
  "name": "紫日",
  "room_id": null,
  "score": 19440,
  "team_id": null,
  "time_to_last": null,
  "user_id": 20938351,
  "won": null,
  "coins_earned": 0,
  "killer_tribe_id": null,
  "killer_tribe_name": null,
  "victim_tribe_id": 2879,
  "victim_tribe_name": "可以瑟瑟嗎",
  "archived_at": "2025-05-29T20:03:03.120Z"
}