{
  "id": 1171823,
  "boosts": 23,
  "date_created": "2022-06-05T19:28:27.000Z",
  "death_count": 1,
  "die_reason": 7,
  "duration": 85,
  "flags": null,
  "flappycombo": 0,
  "gamemode_id": 2,
  "kill_count": 0,
  "killer_level": null,
  "killer_name": null,
  "killer_user_id": null,
  "level": 102,
  "max_leaderboard": null,
  "name": "mlko",
  "room_id": 107287,
  "score": 20225,
  "team_id": 1,
  "time_to_last": null,
  "user_id": 506332,
  "won": false,
  "coins_earned": 0,
  "killer_tribe_id": null,
  "killer_tribe_name": null,
  "victim_tribe_id": null,
  "victim_tribe_name": null,
  "archived_at": "2025-05-29T02:10:39.132Z"
}