{
  "id": 1747425,
  "boosts": 106,
  "date_created": "2022-06-20T06:52:38.000Z",
  "death_count": null,
  "die_reason": 2,
  "duration": 791,
  "flags": 2,
  "flappycombo": 0,
  "gamemode_id": 6,
  "kill_count": 9,
  "killer_level": 31,
  "killer_name": "hận mày H2O",
  "killer_user_id": 20945377,
  "level": 11,
  "max_leaderboard": 8,
  "name": "H2O",
  "room_id": null,
  "score": 598814,
  "team_id": null,
  "time_to_last": null,
  "user_id": 766522,
  "won": null,
  "coins_earned": 9,
  "killer_tribe_id": 2241,
  "killer_tribe_name": "vn",
  "victim_tribe_id": 2155,
  "victim_tribe_name": "Dark ",
  "archived_at": "2025-05-31T12:08:53.208Z"
}