{
  "id": 6505941,
  "boosts": 72,
  "date_created": "2022-10-25T22:41:31.000Z",
  "death_count": null,
  "die_reason": 1,
  "duration": 1659,
  "flags": null,
  "flappycombo": 0,
  "gamemode_id": 6,
  "kill_count": 2,
  "killer_level": null,
  "killer_name": null,
  "killer_user_id": null,
  "level": 12,
  "max_leaderboard": 4,
  "name": "악어씌",
  "room_id": null,
  "score": 339775,
  "team_id": null,
  "time_to_last": null,
  "user_id": 20968662,
  "won": null,
  "coins_earned": 4,
  "killer_tribe_id": null,
  "killer_tribe_name": null,
  "victim_tribe_id": 26841,
  "victim_tribe_name": "장찌상튀김",
  "archived_at": "2025-06-29T07:39:22.496Z"
}