{
  "id": 945059,
  "boosts": 27,
  "date_created": "2022-05-30T16:38:43.000Z",
  "death_count": null,
  "die_reason": 2,
  "duration": 405,
  "flags": 2,
  "flappycombo": 0,
  "gamemode_id": 6,
  "kill_count": 2,
  "killer_level": 40,
  "killer_name": "Team with me to win",
  "killer_user_id": 20720380,
  "level": 97,
  "max_leaderboard": null,
  "name": "Kolaxosaur",
  "room_id": null,
  "score": 92550,
  "team_id": null,
  "time_to_last": null,
  "user_id": 20938840,
  "won": null,
  "coins_earned": 1,
  "killer_tribe_id": null,
  "killer_tribe_name": null,
  "victim_tribe_id": null,
  "victim_tribe_name": null,
  "archived_at": "2025-05-28T02:34:28.748Z"
}