{
  "id": 6393743,
  "boosts": 113,
  "date_created": "2022-10-23T03:40:43.000Z",
  "death_count": null,
  "die_reason": 2,
  "duration": 1492,
  "flags": null,
  "flappycombo": 0,
  "gamemode_id": 1,
  "kill_count": 12,
  "killer_level": 40,
  "killer_name": "🦀CrabHole🦀",
  "killer_user_id": 20962999,
  "level": 10,
  "max_leaderboard": 3,
  "name": "<GRE>Kha<BLU>iZen",
  "room_id": null,
  "score": 1024909,
  "team_id": null,
  "time_to_last": null,
  "user_id": 20961090,
  "won": null,
  "coins_earned": 16,
  "killer_tribe_id": null,
  "killer_tribe_name": null,
  "victim_tribe_id": null,
  "victim_tribe_name": null,
  "archived_at": "2025-06-28T07:35:41.153Z"
}