{
  "id": 3437889,
  "boosts": 52,
  "date_created": "2022-08-08T12:04:44.000Z",
  "death_count": null,
  "die_reason": 2,
  "duration": 657,
  "flags": 2,
  "flappycombo": 0,
  "gamemode_id": 6,
  "kill_count": 7,
  "killer_level": 11,
  "killer_name": "<RED>夜夢<GRE>",
  "killer_user_id": 20821784,
  "level": 11,
  "max_leaderboard": 15,
  "name": "Allln",
  "room_id": null,
  "score": 313490,
  "team_id": null,
  "time_to_last": null,
  "user_id": 666347,
  "won": null,
  "coins_earned": 6,
  "killer_tribe_id": 22900,
  "killer_tribe_name": "夜裡",
  "victim_tribe_id": null,
  "victim_tribe_name": null,
  "archived_at": "2025-06-08T14:21:02.497Z"
}