{
  "id": 6461195,
  "boosts": 23,
  "date_created": "2022-10-24T20:01:04.000Z",
  "death_count": null,
  "die_reason": 7,
  "duration": 116,
  "flags": null,
  "flappycombo": 0,
  "gamemode_id": 6,
  "kill_count": 0,
  "killer_level": null,
  "killer_name": null,
  "killer_user_id": null,
  "level": 105,
  "max_leaderboard": null,
  "name": "manta is stinky",
  "room_id": null,
  "score": 23335,
  "team_id": null,
  "time_to_last": null,
  "user_id": 20754657,
  "won": null,
  "coins_earned": 0,
  "killer_tribe_id": null,
  "killer_tribe_name": null,
  "victim_tribe_id": null,
  "victim_tribe_name": null,
  "archived_at": "2025-06-28T21:07:59.395Z"
}