{
  "id": 1499595,
  "boosts": 47,
  "date_created": "2022-06-13T21:52:40.000Z",
  "death_count": null,
  "die_reason": 2,
  "duration": 268,
  "flags": 2,
  "flappycombo": 0,
  "gamemode_id": 1,
  "kill_count": 1,
  "killer_level": 24,
  "killer_name": "Dingleberg",
  "killer_user_id": 20818611,
  "level": 5,
  "max_leaderboard": null,
  "name": "ACE",
  "room_id": null,
  "score": 73008,
  "team_id": null,
  "time_to_last": null,
  "user_id": 709567,
  "won": null,
  "coins_earned": 1,
  "killer_tribe_id": null,
  "killer_tribe_name": null,
  "victim_tribe_id": null,
  "victim_tribe_name": null,
  "archived_at": "2025-05-30T11:28:22.581Z"
}