{
  "id": 6378603,
  "boosts": 14,
  "date_created": "2022-10-22T19:39:04.000Z",
  "death_count": null,
  "die_reason": 2,
  "duration": 155,
  "flags": null,
  "flappycombo": 0,
  "gamemode_id": 6,
  "kill_count": 4,
  "killer_level": 71,
  "killer_name": null,
  "killer_user_id": 20939696,
  "level": 95,
  "max_leaderboard": null,
  "name": "Modified ",
  "room_id": null,
  "score": 37594,
  "team_id": null,
  "time_to_last": null,
  "user_id": 20966395,
  "won": null,
  "coins_earned": 1,
  "killer_tribe_id": 17937,
  "killer_tribe_name": "eeeee",
  "victim_tribe_id": null,
  "victim_tribe_name": null,
  "archived_at": "2025-06-28T04:31:43.932Z"
}