{
  "id": 6768975,
  "boosts": 167,
  "date_created": "2022-11-01T02:45:44.000Z",
  "death_count": null,
  "die_reason": 2,
  "duration": 858,
  "flags": null,
  "flappycombo": 0,
  "gamemode_id": 1,
  "kill_count": 6,
  "killer_level": 91,
  "killer_name": "-crong-",
  "killer_user_id": 14005738,
  "level": 22,
  "max_leaderboard": 2,
  "name": "goku",
  "room_id": null,
  "score": 732783,
  "team_id": null,
  "time_to_last": null,
  "user_id": 20758000,
  "won": null,
  "coins_earned": 10,
  "killer_tribe_id": null,
  "killer_tribe_name": null,
  "victim_tribe_id": null,
  "victim_tribe_name": null
}