{
  "id": 2716252,
  "boosts": 308,
  "date_created": "2022-07-19T04:45:09.000Z",
  "death_count": null,
  "die_reason": 2,
  "duration": 3301,
  "flags": 2,
  "flappycombo": 0,
  "gamemode_id": 1,
  "kill_count": 18,
  "killer_level": 101,
  "killer_name": "Mola",
  "killer_user_id": 546915,
  "level": 31,
  "max_leaderboard": 2,
  "name": "🦈<RED>BRANSON 🦈",
  "room_id": null,
  "score": 2107421,
  "team_id": null,
  "time_to_last": null,
  "user_id": 20954540,
  "won": null,
  "coins_earned": 35,
  "killer_tribe_id": null,
  "killer_tribe_name": null,
  "victim_tribe_id": null,
  "victim_tribe_name": null,
  "archived_at": "2025-06-05T00:52:40.610Z"
}