{
  "id": 987575,
  "boosts": 103,
  "date_created": "2022-05-31T20:50:28.000Z",
  "death_count": null,
  "die_reason": 2,
  "duration": 1479,
  "flags": 2,
  "flappycombo": 0,
  "gamemode_id": 1,
  "kill_count": 0,
  "killer_level": 11,
  "killer_name": "Deez",
  "killer_user_id": 20941315,
  "level": 11,
  "max_leaderboard": 14,
  "name": "<RED>cl<GRE>o<BLU>wn",
  "room_id": null,
  "score": 337315,
  "team_id": null,
  "time_to_last": null,
  "user_id": 759127,
  "won": null,
  "coins_earned": 7,
  "killer_tribe_id": null,
  "killer_tribe_name": null,
  "victim_tribe_id": null,
  "victim_tribe_name": null,
  "archived_at": "2025-05-28T07:48:36.095Z"
}