{
  "id": 6531304,
  "boosts": 3,
  "date_created": "2022-10-26T15:23:06.000Z",
  "death_count": null,
  "die_reason": 2,
  "duration": 81,
  "flags": null,
  "flappycombo": 0,
  "gamemode_id": 6,
  "kill_count": 0,
  "killer_level": 46,
  "killer_name": "mr. fishy",
  "killer_user_id": null,
  "level": 2,
  "max_leaderboard": null,
  "name": "kriby",
  "room_id": null,
  "score": 18825,
  "team_id": null,
  "time_to_last": null,
  "user_id": 20804278,
  "won": null,
  "coins_earned": 0,
  "killer_tribe_id": 21378,
  "killer_tribe_name": "hi",
  "victim_tribe_id": null,
  "victim_tribe_name": null,
  "archived_at": "2025-06-29T14:07:03.936Z"
}