{
  "id": 172308,
  "boosts": 37,
  "date_created": "2022-03-24T22:38:00.000Z",
  "death_count": null,
  "die_reason": 2,
  "duration": 586,
  "flags": null,
  "flappycombo": 0,
  "gamemode_id": 1,
  "kill_count": 4,
  "killer_level": 45,
  "killer_name": "trung_vn",
  "killer_user_id": 20753825,
  "level": 11,
  "max_leaderboard": null,
  "name": null,
  "room_id": null,
  "score": 206304,
  "team_id": null,
  "time_to_last": null,
  "user_id": 20787569,
  "won": null,
  "coins_earned": 4,
  "killer_tribe_id": null,
  "killer_tribe_name": null,
  "victim_tribe_id": null,
  "victim_tribe_name": null,
  "archived_at": "2025-05-24T15:56:04.738Z"
}