{
  "id": 2093616,
  "boosts": 8,
  "date_created": "2022-06-30T02:18:07.000Z",
  "death_count": null,
  "die_reason": 2,
  "duration": 55,
  "flags": null,
  "flappycombo": 0,
  "gamemode_id": 6,
  "kill_count": 0,
  "killer_level": 61,
  "killer_name": "玩 石頭魚",
  "killer_user_id": 20938552,
  "level": 5,
  "max_leaderboard": null,
  "name": "ㅇㅅㅇ",
  "room_id": null,
  "score": 7100,
  "team_id": null,
  "time_to_last": null,
  "user_id": 20950105,
  "won": null,
  "coins_earned": 0,
  "killer_tribe_id": 7778,
  "killer_tribe_name": "🌰🌰",
  "victim_tribe_id": 7826,
  "victim_tribe_name": "ㅋㅋㅋㅋㅋ",
  "archived_at": "2025-06-02T00:55:18.603Z"
}