{
  "id": 3670376,
  "boosts": 53,
  "date_created": "2022-08-14T19:07:23.000Z",
  "death_count": null,
  "die_reason": 2,
  "duration": 590,
  "flags": 2,
  "flappycombo": 0,
  "gamemode_id": 6,
  "kill_count": 1,
  "killer_level": 111,
  "killer_name": "Pi'erre",
  "killer_user_id": 675738,
  "level": 106,
  "max_leaderboard": 15,
  "name": "GlitchGirl",
  "room_id": null,
  "score": 174057,
  "team_id": null,
  "time_to_last": null,
  "user_id": 20810174,
  "won": null,
  "coins_earned": 3,
  "killer_tribe_id": null,
  "killer_tribe_name": null,
  "victim_tribe_id": 1357,
  "victim_tribe_name": "!?",
  "archived_at": "2025-06-09T20:28:21.567Z"
}