{
  "id": 6166319,
  "boosts": 36,
  "date_created": "2022-10-16T22:48:55.000Z",
  "death_count": null,
  "die_reason": 3,
  "duration": 1042,
  "flags": null,
  "flappycombo": 0,
  "gamemode_id": 1,
  "kill_count": 3,
  "killer_level": null,
  "killer_name": null,
  "killer_user_id": null,
  "level": 83,
  "max_leaderboard": 9,
  "name": "WallmartKSI",
  "room_id": null,
  "score": 258430,
  "team_id": null,
  "time_to_last": null,
  "user_id": 20809959,
  "won": null,
  "coins_earned": 3,
  "killer_tribe_id": null,
  "killer_tribe_name": null,
  "victim_tribe_id": null,
  "victim_tribe_name": null,
  "archived_at": "2025-06-26T21:08:50.470Z"
}