{
  "id": 1384725,
  "boosts": 56,
  "date_created": "2022-06-10T22:32:53.000Z",
  "death_count": null,
  "die_reason": 2,
  "duration": 817,
  "flags": 2,
  "flappycombo": 0,
  "gamemode_id": 1,
  "kill_count": 5,
  "killer_level": 71,
  "killer_name": "а",
  "killer_user_id": null,
  "level": 24,
  "max_leaderboard": 12,
  "name": "500 for pets wtf",
  "room_id": null,
  "score": 434193,
  "team_id": null,
  "time_to_last": null,
  "user_id": 20745942,
  "won": null,
  "coins_earned": 7,
  "killer_tribe_id": null,
  "killer_tribe_name": null,
  "victim_tribe_id": null,
  "victim_tribe_name": null,
  "archived_at": "2025-05-29T23:45:24.830Z"
}