{
  "id": 2019992,
  "boosts": 131,
  "date_created": "2022-06-28T00:39:56.000Z",
  "death_count": null,
  "die_reason": 2,
  "duration": 1103,
  "flags": 2,
  "flappycombo": 0,
  "gamemode_id": 6,
  "kill_count": 4,
  "killer_level": 119,
  "killer_name": "coca cola",
  "killer_user_id": 20822508,
  "level": 22,
  "max_leaderboard": 7,
  "name": "JuanFCI",
  "room_id": null,
  "score": 528046,
  "team_id": null,
  "time_to_last": null,
  "user_id": 610178,
  "won": null,
  "coins_earned": 9,
  "killer_tribe_id": 7158,
  "killer_tribe_name": ".-.",
  "victim_tribe_id": 7178,
  "victim_tribe_name": "josw",
  "archived_at": "2025-06-01T16:29:57.190Z"
}