{
  "id": 3661131,
  "boosts": 9,
  "date_created": "2022-08-14T13:35:27.000Z",
  "death_count": null,
  "die_reason": 2,
  "duration": 159,
  "flags": 2,
  "flappycombo": 0,
  "gamemode_id": 6,
  "kill_count": 1,
  "killer_level": 35,
  "killer_name": "Mini",
  "killer_user_id": null,
  "level": 9,
  "max_leaderboard": 13,
  "name": "Rain",
  "room_id": null,
  "score": 110402,
  "team_id": null,
  "time_to_last": null,
  "user_id": 20742605,
  "won": null,
  "coins_earned": 1,
  "killer_tribe_id": 1052,
  "killer_tribe_name": "ELITE",
  "victim_tribe_id": 1081,
  "victim_tribe_name": "Hi",
  "archived_at": "2025-06-09T19:18:34.812Z"
}