{
  "id": 3317508,
  "boosts": 1,
  "date_created": "2022-08-05T02:18:51.000Z",
  "death_count": null,
  "die_reason": 2,
  "duration": 23,
  "flags": null,
  "flappycombo": 0,
  "gamemode_id": 6,
  "kill_count": 0,
  "killer_level": 97,
  "killer_name": "HJ",
  "killer_user_id": null,
  "level": 78,
  "max_leaderboard": null,
  "name": "KadeIsJustBetter",
  "room_id": null,
  "score": 2900,
  "team_id": null,
  "time_to_last": null,
  "user_id": 20789247,
  "won": null,
  "coins_earned": 0,
  "killer_tribe_id": null,
  "killer_tribe_name": null,
  "victim_tribe_id": null,
  "victim_tribe_name": null,
  "archived_at": "2025-06-07T23:00:23.862Z"
}