{
  "id": 5460432,
  "boosts": 14,
  "date_created": "2022-09-29T15:27:45.000Z",
  "death_count": null,
  "die_reason": 2,
  "duration": 188,
  "flags": null,
  "flappycombo": 0,
  "gamemode_id": 1,
  "kill_count": 2,
  "killer_level": 30,
  "killer_name": "Nick",
  "killer_user_id": 20969913,
  "level": 99,
  "max_leaderboard": null,
  "name": "Tekka0173",
  "room_id": null,
  "score": 28198,
  "team_id": null,
  "time_to_last": null,
  "user_id": 20971551,
  "won": null,
  "coins_earned": 0,
  "killer_tribe_id": null,
  "killer_tribe_name": null,
  "victim_tribe_id": null,
  "victim_tribe_name": null,
  "archived_at": "2025-06-21T08:05:40.110Z"
}