{
  "id": 6170344,
  "boosts": 52,
  "date_created": "2022-10-17T01:47:29.000Z",
  "death_count": 2,
  "die_reason": 7,
  "duration": 271,
  "flags": null,
  "flappycombo": 0,
  "gamemode_id": 2,
  "kill_count": 2,
  "killer_level": null,
  "killer_name": null,
  "killer_user_id": null,
  "level": 111,
  "max_leaderboard": null,
  "name": "THE?",
  "room_id": 159900,
  "score": 108724,
  "team_id": 0,
  "time_to_last": null,
  "user_id": 20959778,
  "won": true,
  "coins_earned": 10,
  "killer_tribe_id": null,
  "killer_tribe_name": null,
  "victim_tribe_id": null,
  "victim_tribe_name": null,
  "archived_at": "2025-06-26T21:56:17.964Z"
}