{
  "id": 2869798,
  "boosts": 14,
  "date_created": "2022-07-23T14:52:14.000Z",
  "death_count": null,
  "die_reason": 2,
  "duration": 253,
  "flags": 2,
  "flappycombo": 0,
  "gamemode_id": 6,
  "kill_count": 1,
  "killer_level": 11,
  "killer_name": "F",
  "killer_user_id": 20956284,
  "level": 81,
  "max_leaderboard": null,
  "name": "BOB",
  "room_id": null,
  "score": 80208,
  "team_id": null,
  "time_to_last": null,
  "user_id": 20771063,
  "won": null,
  "coins_earned": 1,
  "killer_tribe_id": 6964,
  "killer_tribe_name": "peace",
  "victim_tribe_id": 6930,
  "victim_tribe_name": "pArOt",
  "archived_at": "2025-06-05T17:46:54.666Z"
}