{
  "id": 6175496,
  "boosts": 90,
  "date_created": "2022-10-17T07:34:31.000Z",
  "death_count": null,
  "die_reason": 2,
  "duration": 1145,
  "flags": null,
  "flappycombo": 0,
  "gamemode_id": 1,
  "kill_count": 3,
  "killer_level": 11,
  "killer_name": "Ignatius",
  "killer_user_id": 780431,
  "level": 48,
  "max_leaderboard": 5,
  "name": "hi",
  "room_id": null,
  "score": 742286,
  "team_id": null,
  "time_to_last": null,
  "user_id": 20973458,
  "won": null,
  "coins_earned": 9,
  "killer_tribe_id": null,
  "killer_tribe_name": null,
  "victim_tribe_id": null,
  "victim_tribe_name": null,
  "archived_at": "2025-06-26T22:56:30.503Z"
}