{
  "id": 3186930,
  "boosts": 6,
  "date_created": "2022-08-01T13:14:21.000Z",
  "death_count": null,
  "die_reason": 2,
  "duration": 83,
  "flags": null,
  "flappycombo": 0,
  "gamemode_id": 6,
  "kill_count": 0,
  "killer_level": 19,
  "killer_name": "저스틴비버",
  "killer_user_id": 20941089,
  "level": 43,
  "max_leaderboard": null,
  "name": "Karjie",
  "room_id": null,
  "score": 19625,
  "team_id": null,
  "time_to_last": null,
  "user_id": 704022,
  "won": null,
  "coins_earned": 0,
  "killer_tribe_id": 16356,
  "killer_tribe_name": "황보황보!",
  "victim_tribe_id": null,
  "victim_tribe_name": null,
  "archived_at": "2025-06-07T06:16:24.056Z"
}