{
  "id": 6067863,
  "boosts": 24,
  "date_created": "2022-10-14T18:29:26.000Z",
  "death_count": null,
  "die_reason": 2,
  "duration": 209,
  "flags": null,
  "flappycombo": 0,
  "gamemode_id": 1,
  "kill_count": 2,
  "killer_level": 32,
  "killer_name": "The duck song",
  "killer_user_id": null,
  "level": 10,
  "max_leaderboard": 15,
  "name": "<RED> Oragne",
  "room_id": null,
  "score": 406105,
  "team_id": null,
  "time_to_last": null,
  "user_id": 20975041,
  "won": null,
  "coins_earned": 5,
  "killer_tribe_id": null,
  "killer_tribe_name": null,
  "victim_tribe_id": null,
  "victim_tribe_name": null,
  "archived_at": "2025-06-26T01:37:07.683Z"
}