{
  "id": 3209205,
  "boosts": 399,
  "date_created": "2022-08-02T03:18:17.000Z",
  "death_count": null,
  "die_reason": 2,
  "duration": 947,
  "flags": 2,
  "flappycombo": 0,
  "gamemode_id": 6,
  "kill_count": 20,
  "killer_level": 22,
  "killer_name": "오스",
  "killer_user_id": null,
  "level": 111,
  "max_leaderboard": 5,
  "name": "87 of the king",
  "room_id": null,
  "score": 1301044,
  "team_id": null,
  "time_to_last": null,
  "user_id": 20751131,
  "won": null,
  "coins_earned": 20,
  "killer_tribe_id": 16694,
  "killer_tribe_name": "라오스",
  "victim_tribe_id": 16679,
  "victim_tribe_name": "jeomi",
  "archived_at": "2025-06-07T09:06:46.816Z"
}