{
  "id": 2116700,
  "boosts": 424,
  "date_created": "2022-06-30T16:00:40.000Z",
  "death_count": null,
  "die_reason": 2,
  "duration": 14797,
  "flags": 2,
  "flappycombo": 0,
  "gamemode_id": 1,
  "kill_count": 19,
  "killer_level": 111,
  "killer_name": "shy vn",
  "killer_user_id": 20939270,
  "level": 111,
  "max_leaderboard": 1,
  "name": "AKA_咪咪",
  "room_id": null,
  "score": 3386094,
  "team_id": null,
  "time_to_last": null,
  "user_id": 20943935,
  "won": null,
  "coins_earned": 86,
  "killer_tribe_id": null,
  "killer_tribe_name": null,
  "victim_tribe_id": null,
  "victim_tribe_name": null,
  "archived_at": "2025-06-02T03:17:58.215Z"
}