{
  "id": 4441411,
  "boosts": 141,
  "date_created": "2022-09-03T11:15:00.000Z",
  "death_count": null,
  "die_reason": 2,
  "duration": 1676,
  "flags": null,
  "flappycombo": 0,
  "gamemode_id": 6,
  "kill_count": 0,
  "killer_level": 30,
  "killer_name": "cac",
  "killer_user_id": 14006769,
  "level": 106,
  "max_leaderboard": 15,
  "name": "❤Yến Nhyy❤",
  "room_id": null,
  "score": 321340,
  "team_id": null,
  "time_to_last": null,
  "user_id": 20947688,
  "won": null,
  "coins_earned": 4,
  "killer_tribe_id": 18595,
  "killer_tribe_name": ".",
  "victim_tribe_id": 18613,
  "victim_tribe_name": "haha",
  "archived_at": "2025-06-14T10:22:13.501Z"
}