{
  "id": 2946371,
  "boosts": 42,
  "date_created": "2022-07-25T19:14:29.000Z",
  "death_count": null,
  "die_reason": 2,
  "duration": 748,
  "flags": 2,
  "flappycombo": 0,
  "gamemode_id": 6,
  "kill_count": 4,
  "killer_level": 34,
  "killer_name": "Lepi",
  "killer_user_id": 564803,
  "level": 82,
  "max_leaderboard": null,
  "name": "PDD IS ASS",
  "room_id": null,
  "score": 102004,
  "team_id": null,
  "time_to_last": null,
  "user_id": 20799375,
  "won": null,
  "coins_earned": 4,
  "killer_tribe_id": 8563,
  "killer_tribe_name": "ඞ",
  "victim_tribe_id": null,
  "victim_tribe_name": null,
  "archived_at": "2025-06-06T03:16:24.848Z"
}