{
  "id": 3060353,
  "boosts": 20,
  "date_created": "2022-07-28T23:04:05.000Z",
  "death_count": null,
  "die_reason": 2,
  "duration": 459,
  "flags": 2,
  "flappycombo": 0,
  "gamemode_id": 1,
  "kill_count": 3,
  "killer_level": 24,
  "killer_name": "Among us creature",
  "killer_user_id": null,
  "level": 71,
  "max_leaderboard": 7,
  "name": "white",
  "room_id": null,
  "score": 425933,
  "team_id": null,
  "time_to_last": null,
  "user_id": 20775109,
  "won": null,
  "coins_earned": 6,
  "killer_tribe_id": null,
  "killer_tribe_name": null,
  "victim_tribe_id": null,
  "victim_tribe_name": null,
  "archived_at": "2025-06-06T15:54:09.233Z"
}