{
  "id": 1371101,
  "boosts": 80,
  "date_created": "2022-06-10T15:26:42.000Z",
  "death_count": null,
  "die_reason": 2,
  "duration": 1331,
  "flags": 2,
  "flappycombo": 0,
  "gamemode_id": 6,
  "kill_count": 3,
  "killer_level": 34,
  "killer_name": "中国人也骗也骗也偷袭中国人",
  "killer_user_id": 20798980,
  "level": 38,
  "max_leaderboard": null,
  "name": "A gay furry",
  "room_id": null,
  "score": 162369,
  "team_id": null,
  "time_to_last": null,
  "user_id": 20945290,
  "won": null,
  "coins_earned": 6,
  "killer_tribe_id": 3138,
  "killer_tribe_name": "yej",
  "victim_tribe_id": null,
  "victim_tribe_name": null,
  "archived_at": "2025-05-29T22:23:19.452Z"
}