{
  "id": 6529677,
  "boosts": 29,
  "date_created": "2022-10-26T14:49:12.000Z",
  "death_count": null,
  "die_reason": 2,
  "duration": 439,
  "flags": null,
  "flappycombo": 0,
  "gamemode_id": 1,
  "kill_count": 0,
  "killer_level": 32,
  "killer_name": "TRZ",
  "killer_user_id": 20812487,
  "level": 96,
  "max_leaderboard": null,
  "name": "Round Cats",
  "room_id": null,
  "score": 118685,
  "team_id": null,
  "time_to_last": null,
  "user_id": 20979997,
  "won": null,
  "coins_earned": 1,
  "killer_tribe_id": null,
  "killer_tribe_name": null,
  "victim_tribe_id": null,
  "victim_tribe_name": null,
  "archived_at": "2025-06-29T13:39:45.856Z"
}