{
  "id": 6529675,
  "boosts": 21,
  "date_created": "2022-10-26T14:49:09.000Z",
  "death_count": null,
  "die_reason": 2,
  "duration": 516,
  "flags": null,
  "flappycombo": 0,
  "gamemode_id": 6,
  "kill_count": 0,
  "killer_level": 104,
  "killer_name": "IDFC",
  "killer_user_id": 590461,
  "level": 70,
  "max_leaderboard": null,
  "name": "프링글스",
  "room_id": null,
  "score": 120879,
  "team_id": null,
  "time_to_last": null,
  "user_id": 20970354,
  "won": null,
  "coins_earned": 1,
  "killer_tribe_id": 27393,
  "killer_tribe_name": " ",
  "victim_tribe_id": 27425,
  "victim_tribe_name": "귀대",
  "archived_at": "2025-06-29T13:39:45.788Z"
}