{
  "id": 2012580,
  "boosts": 16,
  "date_created": "2022-06-27T19:02:10.000Z",
  "death_count": null,
  "die_reason": 2,
  "duration": 181,
  "flags": null,
  "flappycombo": 0,
  "gamemode_id": 6,
  "kill_count": 0,
  "killer_level": 32,
  "killer_name": "Tempest",
  "killer_user_id": 20950520,
  "level": 90,
  "max_leaderboard": null,
  "name": "Gar",
  "room_id": null,
  "score": 70750,
  "team_id": null,
  "time_to_last": null,
  "user_id": 20795487,
  "won": null,
  "coins_earned": 0,
  "killer_tribe_id": 7043,
  "killer_tribe_name": "SOLO",
  "victim_tribe_id": 7054,
  "victim_tribe_name": "Bask",
  "archived_at": "2025-06-01T15:46:57.663Z"
}