{
  "id": 4937371,
  "boosts": 128,
  "date_created": "2022-09-16T12:08:21.000Z",
  "death_count": null,
  "die_reason": 2,
  "duration": 444,
  "flags": null,
  "flappycombo": 0,
  "gamemode_id": 6,
  "kill_count": 4,
  "killer_level": 22,
  "killer_name": "ì‹ ì˜ ì„œì•½",
  "killer_user_id": 20749717,
  "level": 22,
  "max_leaderboard": 13,
  "name": "ğ™ˆğ™‚æ¯é›",
  "room_id": null,
  "score": 390968,
  "team_id": null,
  "time_to_last": null,
  "user_id": 690749,
  "won": null,
  "coins_earned": 6,
  "killer_tribe_id": null,
  "killer_tribe_name": null,
  "victim_tribe_id": null,
  "victim_tribe_name": null,
  "archived_at": "2025-06-17T18:31:40.372Z"
}