{
  "id": 1813567,
  "boosts": 24,
  "date_created": "2022-06-22T06:28:55.000Z",
  "death_count": null,
  "die_reason": 2,
  "duration": 245,
  "flags": 2,
  "flappycombo": 0,
  "gamemode_id": 1,
  "kill_count": 2,
  "killer_level": 106,
  "killer_name": "Mason",
  "killer_user_id": null,
  "level": 61,
  "max_leaderboard": 6,
  "name": "Lol [WB]",
  "room_id": null,
  "score": 277907,
  "team_id": null,
  "time_to_last": null,
  "user_id": 20945730,
  "won": null,
  "coins_earned": 3,
  "killer_tribe_id": null,
  "killer_tribe_name": null,
  "victim_tribe_id": null,
  "victim_tribe_name": null,
  "archived_at": "2025-05-31T18:41:20.426Z"
}