{
  "id": 6135104,
  "boosts": 57,
  "date_created": "2022-10-16T06:21:28.000Z",
  "death_count": 10,
  "die_reason": 7,
  "duration": 977,
  "flags": null,
  "flappycombo": 0,
  "gamemode_id": 2,
  "kill_count": 3,
  "killer_level": null,
  "killer_name": null,
  "killer_user_id": null,
  "level": 91,
  "max_leaderboard": null,
  "name": "es",
  "room_id": 176635,
  "score": 719005,
  "team_id": 0,
  "time_to_last": null,
  "user_id": 20739010,
  "won": true,
  "coins_earned": 10,
  "killer_tribe_id": null,
  "killer_tribe_name": null,
  "victim_tribe_id": null,
  "victim_tribe_name": null,
  "archived_at": "2025-06-26T14:56:17.446Z"
}