{
  "id": 937041,
  "boosts": 2,
  "date_created": "2022-05-30T11:04:27.000Z",
  "death_count": null,
  "die_reason": 2,
  "duration": 29,
  "flags": null,
  "flappycombo": 0,
  "gamemode_id": 1,
  "kill_count": 0,
  "killer_level": 32,
  "killer_name": "sena",
  "killer_user_id": 20940728,
  "level": 95,
  "max_leaderboard": null,
  "name": "GigaPezChad",
  "room_id": null,
  "score": 7075,
  "team_id": null,
  "time_to_last": null,
  "user_id": 20941736,
  "won": null,
  "coins_earned": 0,
  "killer_tribe_id": null,
  "killer_tribe_name": null,
  "victim_tribe_id": null,
  "victim_tribe_name": null,
  "archived_at": "2025-05-28T01:37:09.032Z"
}