{
  "id": 2286049,
  "boosts": 31,
  "date_created": "2022-07-05T12:25:13.000Z",
  "death_count": null,
  "die_reason": 2,
  "duration": 572,
  "flags": 2,
  "flappycombo": 0,
  "gamemode_id": 6,
  "kill_count": 0,
  "killer_level": 111,
  "killer_name": "Not_GK1.038",
  "killer_user_id": 20789601,
  "level": 43,
  "max_leaderboard": null,
  "name": "Greyson",
  "room_id": null,
  "score": 99740,
  "team_id": null,
  "time_to_last": null,
  "user_id": 20952665,
  "won": null,
  "coins_earned": 1,
  "killer_tribe_id": 4601,
  "killer_tribe_name": "Cool",
  "victim_tribe_id": 4611,
  "victim_tribe_name": "Ban",
  "archived_at": "2025-06-02T22:16:06.569Z"
}