{
  "id": 5039511,
  "boosts": 31,
  "date_created": "2022-09-18T13:33:35.000Z",
  "death_count": null,
  "die_reason": 2,
  "duration": 216,
  "flags": null,
  "flappycombo": 0,
  "gamemode_id": 1,
  "kill_count": 1,
  "killer_level": 46,
  "killer_name": "Casper",
  "killer_user_id": 621145,
  "level": 11,
  "max_leaderboard": null,
  "name": "✨fat✨",
  "room_id": null,
  "score": 111812,
  "team_id": null,
  "time_to_last": null,
  "user_id": 20740301,
  "won": null,
  "coins_earned": 1,
  "killer_tribe_id": null,
  "killer_tribe_name": null,
  "victim_tribe_id": null,
  "victim_tribe_name": null,
  "archived_at": "2025-06-18T10:51:59.576Z"
}