{
  "id": 1393972,
  "boosts": 167,
  "date_created": "2022-06-11T04:08:08.000Z",
  "death_count": null,
  "die_reason": 2,
  "duration": 2262,
  "flags": 2,
  "flappycombo": 0,
  "gamemode_id": 1,
  "kill_count": 3,
  "killer_level": 31,
  "killer_name": "༼ つ ◕_◕ ༽つ",
  "killer_user_id": 20941247,
  "level": 22,
  "max_leaderboard": 3,
  "name": "<BLU>ᴍɪᴋᴀ ʀᴏᴜ",
  "room_id": null,
  "score": 887770,
  "team_id": null,
  "time_to_last": null,
  "user_id": 20824461,
  "won": null,
  "coins_earned": 16,
  "killer_tribe_id": null,
  "killer_tribe_name": null,
  "victim_tribe_id": null,
  "victim_tribe_name": null,
  "archived_at": "2025-05-30T00:43:44.334Z"
}