{
  "id": 4386996,
  "boosts": 58,
  "date_created": "2022-09-02T01:04:36.000Z",
  "death_count": null,
  "die_reason": 2,
  "duration": 1020,
  "flags": null,
  "flappycombo": 0,
  "gamemode_id": 6,
  "kill_count": 0,
  "killer_level": 30,
  "killer_name": "Jordinias!",
  "killer_user_id": 20706483,
  "level": 103,
  "max_leaderboard": 15,
  "name": "Fish Sticks 12",
  "room_id": null,
  "score": 162730,
  "team_id": null,
  "time_to_last": null,
  "user_id": 20959332,
  "won": null,
  "coins_earned": 2,
  "killer_tribe_id": 13355,
  "killer_tribe_name": "🏝",
  "victim_tribe_id": 13400,
  "victim_tribe_name": "boys",
  "archived_at": "2025-06-14T02:39:09.329Z"
}