{
  "id": 2088193,
  "boosts": 18,
  "date_created": "2022-06-29T21:49:15.000Z",
  "death_count": null,
  "die_reason": 2,
  "duration": 703,
  "flags": 2,
  "flappycombo": 0,
  "gamemode_id": 6,
  "kill_count": 0,
  "killer_level": 103,
  "killer_name": "blursed_blob washed",
  "killer_user_id": 20716613,
  "level": 100,
  "max_leaderboard": 15,
  "name": "Volcano ",
  "room_id": null,
  "score": 120370,
  "team_id": null,
  "time_to_last": null,
  "user_id": 20950183,
  "won": null,
  "coins_earned": 3,
  "killer_tribe_id": 518,
  "killer_tribe_name": "Apex",
  "victim_tribe_id": null,
  "victim_tribe_name": null,
  "archived_at": "2025-06-02T00:22:08.954Z"
}