{
  "id": 4701495,
  "boosts": 97,
  "date_created": "2022-09-10T10:38:22.000Z",
  "death_count": null,
  "die_reason": 2,
  "duration": 1507,
  "flags": null,
  "flappycombo": 0,
  "gamemode_id": 1,
  "kill_count": 23,
  "killer_level": 108,
  "killer_name": "pumba",
  "killer_user_id": 20952555,
  "level": 119,
  "max_leaderboard": 5,
  "name": "SpamSandwich",
  "room_id": null,
  "score": 1369027,
  "team_id": null,
  "time_to_last": null,
  "user_id": 20969530,
  "won": null,
  "coins_earned": 23,
  "killer_tribe_id": null,
  "killer_tribe_name": null,
  "victim_tribe_id": null,
  "victim_tribe_name": null,
  "archived_at": "2025-06-16T03:09:24.340Z"
}