{
  "id": 370732,
  "boosts": 31,
  "date_created": "2022-04-16T21:48:40.000Z",
  "death_count": null,
  "die_reason": 2,
  "duration": 160,
  "flags": null,
  "flappycombo": 0,
  "gamemode_id": 1,
  "kill_count": 0,
  "killer_level": 10,
  "killer_name": "LOL",
  "killer_user_id": 20756378,
  "level": 21,
  "max_leaderboard": null,
  "name": "👑💀CORONAVIRUS💀👑",
  "room_id": null,
  "score": 49095,
  "team_id": null,
  "time_to_last": null,
  "user_id": 20747518,
  "won": null,
  "coins_earned": 0,
  "killer_tribe_id": null,
  "killer_tribe_name": null,
  "victim_tribe_id": null,
  "victim_tribe_name": null,
  "archived_at": "2025-05-25T12:22:38.876Z"
}