{
  "id": 6571277,
  "boosts": 0,
  "date_created": "2022-10-27T14:24:12.000Z",
  "death_count": null,
  "die_reason": 2,
  "duration": 118,
  "flags": null,
  "flappycombo": 0,
  "gamemode_id": 6,
  "kill_count": 0,
  "killer_level": 68,
  "killer_name": "Puppy",
  "killer_user_id": null,
  "level": 105,
  "max_leaderboard": null,
  "name": "Horsey",
  "room_id": null,
  "score": 18950,
  "team_id": null,
  "time_to_last": null,
  "user_id": 20975908,
  "won": null,
  "coins_earned": 0,
  "killer_tribe_id": 22261,
  "killer_tribe_name": "MC",
  "victim_tribe_id": null,
  "victim_tribe_name": null,
  "archived_at": "2025-06-30T00:18:01.306Z"
}