{
  "id": 1417626,
  "boosts": 297,
  "date_created": "2022-06-11T17:51:41.000Z",
  "death_count": null,
  "die_reason": 2,
  "duration": 3412,
  "flags": 2,
  "flappycombo": 0,
  "gamemode_id": 6,
  "kill_count": 22,
  "killer_level": 96,
  "killer_name": null,
  "killer_user_id": 20806204,
  "level": 11,
  "max_leaderboard": 3,
  "name": "Orca",
  "room_id": null,
  "score": 2048523,
  "team_id": null,
  "time_to_last": null,
  "user_id": 20944863,
  "won": null,
  "coins_earned": 35,
  "killer_tribe_id": 4230,
  "killer_tribe_name": "ROYAL",
  "victim_tribe_id": 4232,
  "victim_tribe_name": " ",
  "archived_at": "2025-05-30T03:07:53.487Z"
}