{
  "id": 6128250,
  "boosts": 8,
  "date_created": "2022-10-16T02:12:15.000Z",
  "death_count": null,
  "die_reason": 2,
  "duration": 21,
  "flags": null,
  "flappycombo": 0,
  "gamemode_id": 6,
  "kill_count": 0,
  "killer_level": 111,
  "killer_name": null,
  "killer_user_id": null,
  "level": 14,
  "max_leaderboard": null,
  "name": "小燈泡掉頭就走",
  "room_id": null,
  "score": 4250,
  "team_id": null,
  "time_to_last": null,
  "user_id": 20956710,
  "won": null,
  "coins_earned": 0,
  "killer_tribe_id": null,
  "killer_tribe_name": null,
  "victim_tribe_id": null,
  "victim_tribe_name": null,
  "archived_at": "2025-06-26T13:33:49.272Z"
}