{
  "id": 4190003,
  "boosts": 41,
  "date_created": "2022-08-27T21:09:26.000Z",
  "death_count": null,
  "die_reason": 2,
  "duration": 743,
  "flags": null,
  "flappycombo": 0,
  "gamemode_id": 6,
  "kill_count": 3,
  "killer_level": 11,
  "killer_name": "かよ",
  "killer_user_id": 20963838,
  "level": 30,
  "max_leaderboard": 3,
  "name": null,
  "room_id": null,
  "score": 777602,
  "team_id": null,
  "time_to_last": null,
  "user_id": 20744169,
  "won": null,
  "coins_earned": 10,
  "killer_tribe_id": 13469,
  "killer_tribe_name": "リア充死ね",
  "victim_tribe_id": null,
  "victim_tribe_name": null,
  "archived_at": "2025-06-12T21:23:28.961Z"
}