{
  "id": 1095004,
  "boosts": 33,
  "date_created": "2022-06-03T18:57:46.000Z",
  "death_count": 1,
  "die_reason": 7,
  "duration": 201,
  "flags": null,
  "flappycombo": 0,
  "gamemode_id": 2,
  "kill_count": 2,
  "killer_level": null,
  "killer_name": null,
  "killer_user_id": null,
  "level": 11,
  "max_leaderboard": null,
  "name": "ğ“«ğ“¼ğ“­ğ“¾ğ“»ğ“¼ğ“¸ğ“·ğ”¾ğ•",
  "room_id": 158339,
  "score": 134612,
  "team_id": 0,
  "time_to_last": null,
  "user_id": 20813969,
  "won": false,
  "coins_earned": 0,
  "killer_tribe_id": null,
  "killer_tribe_name": null,
  "victim_tribe_id": null,
  "victim_tribe_name": null,
  "archived_at": "2025-05-28T18:30:13.319Z"
}