{
  "id": 5436423,
  "boosts": 51,
  "date_created": "2022-09-28T21:37:28.000Z",
  "death_count": null,
  "die_reason": 2,
  "duration": 530,
  "flags": null,
  "flappycombo": 0,
  "gamemode_id": 1,
  "kill_count": 4,
  "killer_level": 91,
  "killer_name": "die",
  "killer_user_id": 20690137,
  "level": 107,
  "max_leaderboard": null,
  "name": "Orangaglad",
  "room_id": null,
  "score": 266851,
  "team_id": null,
  "time_to_last": null,
  "user_id": 20797267,
  "won": null,
  "coins_earned": 4,
  "killer_tribe_id": null,
  "killer_tribe_name": null,
  "victim_tribe_id": null,
  "victim_tribe_name": null,
  "archived_at": "2025-06-21T04:06:06.970Z"
}