{
  "id": 762672,
  "boosts": 27,
  "date_created": "2022-05-25T15:48:17.000Z",
  "death_count": null,
  "die_reason": 2,
  "duration": 520,
  "flags": 2,
  "flappycombo": 0,
  "gamemode_id": 6,
  "kill_count": 0,
  "killer_level": 24,
  "killer_name": "gay whale :)",
  "killer_user_id": 20813592,
  "level": 21,
  "max_leaderboard": null,
  "name": "Aspect_0",
  "room_id": null,
  "score": 89700,
  "team_id": null,
  "time_to_last": null,
  "user_id": 749731,
  "won": null,
  "coins_earned": 1,
  "killer_tribe_id": 344,
  "killer_tribe_name": "WDC",
  "victim_tribe_id": 384,
  "victim_tribe_name": "SQUID",
  "archived_at": "2025-05-27T07:59:58.225Z"
}