{
  "id": 2079000,
  "boosts": 20,
  "date_created": "2022-06-29T16:16:28.000Z",
  "death_count": 5,
  "die_reason": 7,
  "duration": 393,
  "flags": null,
  "flappycombo": 0,
  "gamemode_id": 2,
  "kill_count": 0,
  "killer_level": null,
  "killer_name": null,
  "killer_user_id": null,
  "level": 34,
  "max_leaderboard": null,
  "name": "pablo",
  "room_id": 189657,
  "score": 107325,
  "team_id": 0,
  "time_to_last": null,
  "user_id": 20943003,
  "won": false,
  "coins_earned": 0,
  "killer_tribe_id": null,
  "killer_tribe_name": null,
  "victim_tribe_id": null,
  "victim_tribe_name": null,
  "archived_at": "2025-06-01T23:10:08.074Z"
}