{
  "id": 4606540,
  "boosts": 52,
  "date_created": "2022-09-07T23:53:12.000Z",
  "death_count": null,
  "die_reason": 2,
  "duration": 1265,
  "flags": null,
  "flappycombo": 0,
  "gamemode_id": 6,
  "kill_count": 0,
  "killer_level": 10,
  "killer_name": "Anubis",
  "killer_user_id": 432765,
  "level": 31,
  "max_leaderboard": 15,
  "name": "Sumangu",
  "room_id": null,
  "score": 180365,
  "team_id": null,
  "time_to_last": null,
  "user_id": 20952945,
  "won": null,
  "coins_earned": 2,
  "killer_tribe_id": null,
  "killer_tribe_name": null,
  "victim_tribe_id": null,
  "victim_tribe_name": null,
  "archived_at": "2025-06-15T11:27:08.520Z"
}