{
  "id": 2224556,
  "boosts": 104,
  "date_created": "2022-07-03T15:16:28.000Z",
  "death_count": null,
  "die_reason": 2,
  "duration": 7,
  "flags": 2,
  "flappycombo": 0,
  "gamemode_id": 1,
  "kill_count": 0,
  "killer_level": 34,
  "killer_name": "FREE WILLY",
  "killer_user_id": null,
  "level": 40,
  "max_leaderboard": 11,
  "name": "yair_17",
  "room_id": null,
  "score": 246315,
  "team_id": null,
  "time_to_last": null,
  "user_id": 20947608,
  "won": null,
  "coins_earned": 2,
  "killer_tribe_id": null,
  "killer_tribe_name": null,
  "victim_tribe_id": null,
  "victim_tribe_name": null,
  "archived_at": "2025-06-02T15:05:14.952Z"
}