{
  "id": 641524,
  "boosts": 10,
  "date_created": "2022-05-19T19:50:05.000Z",
  "death_count": null,
  "die_reason": 2,
  "duration": 517,
  "flags": 2,
  "flappycombo": 0,
  "gamemode_id": 6,
  "kill_count": 0,
  "killer_level": 31,
  "killer_name": "QT Luvs U",
  "killer_user_id": 20938443,
  "level": 5,
  "max_leaderboard": 15,
  "name": "DUSK",
  "room_id": null,
  "score": 57430,
  "team_id": null,
  "time_to_last": null,
  "user_id": 611447,
  "won": null,
  "coins_earned": 1,
  "killer_tribe_id": 2813,
  "killer_tribe_name": "lolls",
  "victim_tribe_id": 2847,
  "victim_tribe_name": "A+",
  "archived_at": "2025-05-26T19:27:47.790Z"
}