{
  "id": 4102629,
  "boosts": 202,
  "date_created": "2022-08-25T16:57:34.000Z",
  "death_count": null,
  "die_reason": 2,
  "duration": 2937,
  "flags": null,
  "flappycombo": 0,
  "gamemode_id": 1,
  "kill_count": 10,
  "killer_level": 30,
  "killer_name": "Torent",
  "killer_user_id": 619106,
  "level": 11,
  "max_leaderboard": 3,
  "name": "Kaan",
  "room_id": null,
  "score": 1114144,
  "team_id": null,
  "time_to_last": null,
  "user_id": 20963641,
  "won": null,
  "coins_earned": 16,
  "killer_tribe_id": null,
  "killer_tribe_name": null,
  "victim_tribe_id": null,
  "victim_tribe_name": null,
  "archived_at": "2025-06-12T06:54:57.738Z"
}