{
  "id": 2442820,
  "boosts": 18,
  "date_created": "2022-07-11T01:51:59.000Z",
  "death_count": null,
  "die_reason": 2,
  "duration": 749,
  "flags": 2,
  "flappycombo": 0,
  "gamemode_id": 1,
  "kill_count": 0,
  "killer_level": 32,
  "killer_name": "BIGMAN",
  "killer_user_id": 20953194,
  "level": 27,
  "max_leaderboard": null,
  "name": "Bletch",
  "room_id": null,
  "score": 48705,
  "team_id": null,
  "time_to_last": null,
  "user_id": 54606,
  "won": null,
  "coins_earned": 2,
  "killer_tribe_id": null,
  "killer_tribe_name": null,
  "victim_tribe_id": null,
  "victim_tribe_name": null,
  "archived_at": "2025-06-03T17:10:30.860Z"
}